{"invoice_id":"24073395-d9c8-48d0-869e-4214abb6d95d","timestamp":"2025-07-13T22:25:41.318895","total_amount":1176.84,"customer":{"customer_id":"CUST-828779","first_name":"Laurie","last_name":"Boyd","email":"laurie.boyd@williams-smith.net","segment":"Premium","loyalty_status":"Bronze","age":"51"},"store":{"store_id":"NYC-001","name":"Manhattan Downtown","city":"New York","state":"NY","region":"Northeast"},"payment_method":"credit_card"}
{"invoice_id":"b691458b-2d62-449b-82a9-e94c55c71bff","timestamp":"2025-07-13T22:25:43.719448","total_amount":52.18,"customer":{"customer_id":"CUST-483934","first_name":"Edward","last_name":"Salinas","email":"edward.salinas@hernandez-munoz.com","segment":"Regular","loyalty_status":"None","age":"18"},"store":{"store_id":"BOS-001","name":"Back Bay","city":"Boston","state":"MA","region":"Northeast"},"payment_method":"credit_card"}
{"invoice_id":"148f19cb-9819-4be8-b2f4-f9fc5c826a82","timestamp":"2025-07-13T22:25:44.919676","total_amount":92.52,"customer":{"customer_id":"CUST-002725","first_name":"Antonio","last_name":"Davis","email":"antonio.davis@gonzales.info","segment":"Budget","loyalty_status":"Platinum","age":"28"},"store":{"store_id":"CHI-001","name":"Magnificent Mile","city":"Chicago","state":"IL","region":"Midwest"},"payment_method":"digital_wallet"}
{"invoice_id":"a3f3b272-7ad7-4723-a1b5-54be73462f2a","timestamp":"2025-07-13T22:25:47.195922","total_amount":1389.56,"customer":{"customer_id":"CUST-000860","first_name":"Bradley","last_name":"Pham","email":"bradley.pham@dixon-holder.info","segment":"Regular","loyalty_status":"Gold","age":"22"},"store":{"store_id":"MIA-001","name":"South Beach","city":"Miami","state":"FL","region":"Southeast"},"payment_method":"digital_wallet"}
