{"invoice_id":"422b12e4-40b0-48f5-b2e7-a2451991a567","timestamp":"2025-07-13T22:32:01.514410","total_amount":132.82,"customer":{"customer_id":"CUST-002984","first_name":"Bryan","last_name":"Bell","email":"bryan.bell@friedman.com","segment":"Regular","loyalty_status":"Gold","age":"59"},"store":{"store_id":"DAL-001","name":"Deep Ellum","city":"Dallas","state":"TX","region":"Southwest"},"payment_method":"credit_card"}
{"invoice_id":"85f3828b-9b7e-401c-ab51-0f70b3d22ada","timestamp":"2025-07-13T22:32:05.115197","total_amount":2499.3,"customer":{"customer_id":"CUST-004093","first_name":"Steven","last_name":"Weber","email":"steven.weber@miller-andrade.org","segment":"Regular","loyalty_status":"Bronze","age":"48"},"store":{"store_id":"MIA-001","name":"South Beach","city":"Miami","state":"FL","region":"Southeast"},"payment_method":"credit_card"}
