{"invoice_id":"d3c0ae6c-1b2a-4035-9dc6-73a42bfa7202","timestamp":"2025-07-13T22:30:37.835420","total_amount":2100.25,"customer":{"customer_id":"CUST-001857","first_name":"Angela","last_name":"Barnett","email":"angela.barnett@taylor-webb.com","segment":"Regular","loyalty_status":"Silver","age":"59"},"store":{"store_id":"DAL-001","name":"Deep Ellum","city":"Dallas","state":"TX","region":"Southwest"},"payment_method":"credit_card"}
{"invoice_id":"65df1e19-14ec-48c5-8a7c-e5f5ecf9cf23","timestamp":"2025-07-13T22:30:43.838248","total_amount":303.41,"customer":{"customer_id":"CUST-003484","first_name":"Christopher","last_name":"Castro","email":"christopher.castro@thomas.com","segment":"Premium","loyalty_status":"Gold","age":"32"},"store":{"store_id":"SF-001","name":"Union Square","city":"San Francisco","state":"CA","region":"West"},"payment_method":"credit_card"}
