{"invoice_id":"99e4c24f-dc98-4559-8c38-47b8cc09694b","timestamp":"2025-07-13T22:29:17.635056","total_amount":1899.87,"customer":{"customer_id":"CUST-005122","first_name":"Randy","last_name":"Nichols","email":"randy.nichols@mendoza.info","segment":"Regular","loyalty_status":"Gold","age":"54"},"store":{"store_id":"SEA-001","name":"Pike Place","city":"Seattle","state":"WA","region":"Northwest"},"payment_method":"credit_card"}
{"invoice_id":"0e892bc4-f02d-42bc-8194-80975ed3f06d","timestamp":"2025-07-13T22:29:18.835288","total_amount":1976.89,"customer":{"customer_id":"CUST-009818","first_name":"Michelle","last_name":"Cross","email":"michelle.cross@williamson.net","segment":"Regular","loyalty_status":"Bronze","age":"31"},"store":{"store_id":"ATL-001","name":"Buckhead","city":"Atlanta","state":"GA","region":"Southeast"},"payment_method":"credit_card"}
